{
    "Beginner": {
        "starting-tablet-count": 3,
        "open-thunderhead": "Ballad",
        "starting-sword": "Goddess Sword",
         "required-dungeon-count": 3,
        "imp2-skip": true,
        "empty-unrequired-dungeons": true,
        "banned-types": ["minigame", "peatrice", "goddess", "medium", "expensive"],
        "triforce-required": false,
        "triforce-shuffle": "Vanilla",
        "seed": -1,
        "hero-mode": false,
        "randomize-entrances": "None",
        "randomize-trials": false,
        "start-with-pouch": true,
        "max-batreaux-reward": 50,
        "shop-mode": "Randomized",
        "rupoor-mode": "Added",
        "rupeesanity": "Vanilla",
        "gondo-upgrades": true,
        "got-start": "Lowered",
        "got-sword-requirement": "True Master Sword",
        "got-dungeon-requirement": "Required",
        "open-lmf": "Open",
        "skip-horde": false,
        "skip-g3": false,
        "skip-demise": false,
        "map-mode": "Own Dungeon - Restricted",
        "small-key-mode": "Lanayru Caves Key Only",
        "boss-key-mode": "Own Dungeon",
        "logic-mode": "BiTless",
        "enabled-tricks-bitless": [],
        "enabled-tricks-glitched": [],
        "song-hints": "None",
        "fix-bit-crashes": false,
        "impa-sot-hint": false,
        "sword-dungeon-reward": false,
        "open-et": true,
        "demise-count": 1,
        "cube-sots": false,
        "precise-item": false,
        "shuffle-trial-objects": "None",
        "chest-dowsing": "None",
        "hint-distribution": "Balanced"
    },
    "3D Rupeesanity": {
        "starting-tablet-count": 1,
        "open-thunderhead": "Ballad",
        "starting-sword": "Goddess Sword",
        "required-dungeon-count": 3,
        "imp2-skip": true,
        "empty-unrequired-dungeons": true,
        "banned-types": ["minigame", "peatrice", "goddess", "medium", "expensive"],
        "triforce-required": true,
        "triforce-shuffle": "Anywhere",
        "seed": -1,
        "hero-mode": true,
        "randomize-entrances": "None",
        "randomize-trials": false,
        "start-with-pouch": true,
        "max-batreaux-reward": 50,
        "shop-mode": "Randomized",
        "rupoor-mode": "Added",
        "rupeesanity": "All",
        "gondo-upgrades": true,
        "got-start": "Lowered",
        "got-sword-requirement": "Master Sword",
        "got-dungeon-requirement": "Required",
        "open-lmf": "Main Node",
        "skip-horde": false,
        "skip-g3": false,
        "skip-demise": false,
        "map-mode": "Own Dungeon - Restricted",
        "small-key-mode": "Lanayru Caves Key Only",
        "boss-key-mode": "Own Dungeon",
        "logic-mode": "BiTless",
        "enabled-tricks-bitless": [],
        "enabled-tricks-glitched": [],
        "song-hints": "None",
        "fix-bit-crashes": false,
        "impa-sot-hint": false,
        "sword-dungeon-reward": false,
        "open-et": true,
        "demise-count": 1,
        "cube-sots": false,
        "precise-item": false,
        "shuffle-trial-objects": "Full",
        "chest-dowsing": "None",
        "hint-distribution": "S2 - 3D"
    },
    "Allsanity": {
        "starting-tablet-count": 3,
        "open-thunderhead": "Ballad",
        "starting-sword": "Swordless",
         "required-dungeon-count": 6,
        "imp2-skip": true,
        "empty-unrequired-dungeons": false,
        "banned-types": [],
        "triforce-required": true,
        "triforce-shuffle": "Anywhere",
        "seed": -1,
        "hero-mode": true,
        "randomize-entrances": "All Dungeons + Sky Keep",
        "randomize-trials": true,
        "start-with-pouch": false,
        "max-batreaux-reward": 80,
        "shop-mode": "Randomized",
        "rupoor-mode": "Added",
        "rupeesanity": "All",
        "gondo-upgrades": true,
        "got-start": "Lowered",
        "got-sword-requirement": "True Master Sword",
        "got-dungeon-requirement": "Required",
        "open-lmf": "Main Node",
        "skip-horde": true,
        "skip-g3": false,
        "skip-demise": false,
        "map-mode": "Own Dungeon - Restricted",
        "small-key-mode": "Anywhere",
        "boss-key-mode": "Anywhere",
        "logic-mode": "BiTless",
        "enabled-tricks-bitless": [],
        "enabled-tricks-glitched": [],
        "song-hints": "None",
        "fix-bit-crashes": false,
        "impa-sot-hint": true,
        "sword-dungeon-reward": false,
        "open-et": true,
        "demise-count": 1,
        "cube-sots": true,
        "precise-item": false,
        "shuffle-trial-objects": "Full",
        "chest-dowsing": "None",
        "hint-distribution": "S2 - 3D EUD Off"
    },
    "S2 - 3D Standard": {
        "starting-tablet-count": 1,
        "open-thunderhead": "Ballad",
        "starting-sword": "Goddess Sword",
        "required-dungeon-count": 3,
        "imp2-skip": true,
        "empty-unrequired-dungeons": true,
        "banned-types": ["minigame", "peatrice", "goddess", "medium", "expensive", "flooded faron"],
        "triforce-required": false,
        "triforce-shuffle": "Vanilla",
        "seed": -1,
        "hero-mode": true,
        "randomize-entrances": "None",
        "randomize-trials": false,
        "start-with-pouch": true,
        "max-batreaux-reward": 50,
        "shop-mode": "Randomized",
        "rupoor-mode": "Added",
        "rupeesanity": "Vanilla",
        "gondo-upgrades": false,
        "got-start": "Lowered",
        "got-sword-requirement": "Master Sword",
        "got-dungeon-requirement": "Required",
        "open-lmf": "Open",
        "skip-horde": false,
        "skip-g3": false,
        "skip-demise": false,
        "map-mode": "Own Dungeon - Restricted",
        "small-key-mode": "Lanayru Caves Key Only",
        "boss-key-mode": "Own Dungeon",
        "logic-mode": "BiTless",
        "enabled-tricks-bitless": [],
        "enabled-tricks-glitched": [],
        "song-hints": "None",
        "fix-bit-crashes": false,
        "impa-sot-hint": false,
        "sword-dungeon-reward": false,
        "open-et": true,
        "demise-count": 1,
        "cube-sots": false,
        "precise-item": false,
        "shuffle-trial-objects": "None",
        "chest-dowsing": "None",
        "hint-distribution": "S2 - 3D"
    },
    "S2 - 2D Cubes": {
        "starting-tablet-count": 1,
        "open-thunderhead": "Ballad",
        "starting-sword": "Goddess Sword",
        "required-dungeon-count": 2,
        "imp2-skip": true,
        "empty-unrequired-dungeons": true,
        "banned-types": ["minigame", "peatrice", "medium", "expensive", "flooded faron"],
        "triforce-required": false,
        "triforce-shuffle": "Vanilla",
        "seed": -1,
        "hero-mode": true,
        "randomize-entrances": "None",
        "randomize-trials": false,
        "start-with-pouch": true,
        "max-batreaux-reward": 50,
        "shop-mode": "Randomized",
        "rupoor-mode": "Added",
        "rupeesanity": "Vanilla",
        "gondo-upgrades": false,
        "got-start": "Lowered",
        "got-sword-requirement": "Master Sword",
        "got-dungeon-requirement": "Required",
        "open-lmf": "Open",
        "skip-horde": false,
        "skip-g3": false,
        "skip-demise": false,
        "map-mode": "Own Dungeon - Restricted",
        "small-key-mode": "Lanayru Caves Key Only",
        "boss-key-mode": "Own Dungeon",
        "logic-mode": "BiTless",
        "enabled-tricks-bitless": [],
        "enabled-tricks-glitched": [],
        "song-hints": "None",
        "fix-bit-crashes": false,
        "impa-sot-hint": false,
        "sword-dungeon-reward": false,
        "open-et": true,
        "demise-count": 1,
        "cube-sots": false,
        "precise-item": false,
        "shuffle-trial-objects": "None",
        "chest-dowsing": "None",
        "hint-distribution": "S2 - 2D"
    },
    "S2 - 3D Open": {
        "starting-tablet-count": 3,
        "open-thunderhead": "Open",
        "starting-sword": "Goddess Sword",
        "required-dungeon-count": 3,
        "imp2-skip": true,
        "empty-unrequired-dungeons": true,
        "banned-types": ["peatrice", "goddess", "medium", "expensive", "flooded faron"],
        "triforce-required": false,
        "triforce-shuffle": "Vanilla",
        "seed": -1,
        "hero-mode": true,
        "randomize-entrances": "None",
        "randomize-trials": false,
        "start-with-pouch": true,
        "max-batreaux-reward": 50,
        "shop-mode": "Randomized",
        "rupoor-mode": "Added",
        "rupeesanity": "Vanilla",
        "gondo-upgrades": false,
        "got-start": "Lowered",
        "got-sword-requirement": "Master Sword",
        "got-dungeon-requirement": "Required",
        "open-lmf": "Open",
        "skip-horde": false,
        "skip-g3": false,
        "skip-demise": false,
        "map-mode": "Own Dungeon - Restricted",
        "small-key-mode": "Lanayru Caves Key Only",
        "boss-key-mode": "Own Dungeon",
        "logic-mode": "BiTless",
        "enabled-tricks-bitless": [],
        "enabled-tricks-glitched": [],
        "song-hints": "None",
        "fix-bit-crashes": false,
        "impa-sot-hint": false,
        "sword-dungeon-reward": false,
        "open-et": true,
        "demise-count": 1,
        "cube-sots": false,
        "precise-item": false,
        "shuffle-trial-objects": "None",
        "chest-dowsing": "None",
        "hint-distribution": "S2 - 3D"
    },
    "S2 - 3D Swordless": {
        "starting-tablet-count": 3,
        "open-thunderhead": "Ballad",
        "starting-sword": "Swordless",
        "required-dungeon-count": 3,
        "imp2-skip": true,
        "empty-unrequired-dungeons": true,
        "banned-types": ["minigame", "peatrice", "goddess", "medium", "expensive", "flooded faron"],
        "triforce-required": false,
        "triforce-shuffle": "Vanilla",
        "seed": -1,
        "hero-mode": true,
        "randomize-entrances": "None",
        "randomize-trials": false,
        "start-with-pouch": true,
        "max-batreaux-reward": 50,
        "shop-mode": "Randomized",
        "rupoor-mode": "Added",
        "rupeesanity": "Vanilla",
        "gondo-upgrades": false,
        "got-start": "Lowered",
        "got-sword-requirement": "Master Sword",
        "got-dungeon-requirement": "Required",
        "open-lmf": "Open",
        "skip-horde": false,
        "skip-g3": false,
        "skip-demise": false,
        "map-mode": "Own Dungeon - Restricted",
        "small-key-mode": "Lanayru Caves Key Only",
        "boss-key-mode": "Own Dungeon",
        "logic-mode": "BiTless",
        "enabled-tricks-bitless": [],
        "enabled-tricks-glitched": [],
        "song-hints": "None",
        "fix-bit-crashes": false,
        "impa-sot-hint": false,
        "sword-dungeon-reward": true,
        "open-et": true,
        "demise-count": 1,
        "cube-sots": false,
        "precise-item": false,
        "shuffle-trial-objects": "None",
        "chest-dowsing": "None",
        "hint-distribution": "S2 - 3D"
    },
    "S2 - 3D EUD Off": {
        "starting-tablet-count": 3,
        "open-thunderhead": "Ballad",
        "starting-sword": "Goddess Sword",
        "required-dungeon-count": 3,
        "imp2-skip": true,
        "empty-unrequired-dungeons": false,
        "banned-types": ["minigame", "peatrice", "goddess", "medium", "expensive", "flooded faron"],
        "triforce-required": false,
        "triforce-shuffle": "Vanilla",
        "seed": -1,
        "hero-mode": true,
        "randomize-entrances": "None",
        "randomize-trials": false,
        "start-with-pouch": true,
        "max-batreaux-reward": 50,
        "shop-mode": "Randomized",
        "rupoor-mode": "Added",
        "rupeesanity": "Vanilla",
        "gondo-upgrades": false,
        "got-start": "Lowered",
        "got-sword-requirement": "Master Sword",
        "got-dungeon-requirement": "Required",
        "open-lmf": "Open",
        "skip-horde": false,
        "skip-g3": false,
        "skip-demise": false,
        "map-mode": "Own Dungeon - Restricted",
        "small-key-mode": "Lanayru Caves Key Only",
        "boss-key-mode": "Own Dungeon",
        "logic-mode": "BiTless",
        "enabled-tricks-bitless": [],
        "enabled-tricks-glitched": [],
        "song-hints": "None",
        "fix-bit-crashes": false,
        "impa-sot-hint": false,
        "sword-dungeon-reward": true,
        "open-et": true,
        "demise-count": 1,
        "cube-sots": false,
        "precise-item": false,
        "shuffle-trial-objects": "None",
        "chest-dowsing": "None",
        "hint-distribution": "S2 - 3D EUD Off"
    },
    "S2 - Keysanity": {
        "starting-tablet-count": 3,
        "open-thunderhead": "Ballad",
        "starting-sword": "Goddess Sword",
        "required-dungeon-count": 3,
        "imp2-skip": true,
        "empty-unrequired-dungeons": true,
        "banned-types": ["minigame", "peatrice", "goddess", "medium", "expensive", "flooded faron"],
        "triforce-required": false,
        "triforce-shuffle": "Vanilla",
        "seed": -1,
        "hero-mode": true,
        "randomize-entrances": "None",
        "randomize-trials": false,
        "start-with-pouch": true,
        "max-batreaux-reward": 50,
        "shop-mode": "Randomized",
        "rupoor-mode": "Added",
        "rupeesanity": "Vanilla",
        "gondo-upgrades": false,
        "got-start": "Lowered",
        "got-sword-requirement": "Master Sword",
        "got-dungeon-requirement": "Required",
        "open-lmf": "Open",
        "skip-horde": false,
        "skip-g3": false,
        "skip-demise": false,
        "map-mode": "Own Dungeon - Restricted",
        "small-key-mode": "Anywhere",
        "boss-key-mode": "Anywhere",
        "logic-mode": "BiTless",
        "enabled-tricks-bitless": [],
        "enabled-tricks-glitched": [],
        "song-hints": "None",
        "fix-bit-crashes": false,
        "impa-sot-hint": false,
        "sword-dungeon-reward": false,
        "open-et": true,
        "demise-count": 1,
        "cube-sots": false,
        "precise-item": false,
        "shuffle-trial-objects": "None",
        "chest-dowsing": "None",
        "hint-distribution": "S2 - 3D"
    }
}